duxueyuan/Square.py
duxueyuan/__init__.py
duxueyuan/__main__.py
duxueyuan/duxueyuan.py
duxueyuan/myfunctions.py
square/Square1.py
square/__init__.py
square/__main__.py
duxueyuan-1.0.16.dist-info/METADATA
duxueyuan-1.0.16.dist-info/WHEEL
duxueyuan-1.0.16.dist-info/entry_points.txt
duxueyuan-1.0.16.dist-info/top_level.txt
duxueyuan-1.0.16.dist-info/RECORD
