Metadata-Version: 2.1
Name: duxueyuan
Version: 1.0.16
Summary: It squares the number
Home-page: https://github.com/wwwxqq/duxueyuan
Author: Xueyuan Du
Author-email: aaa@aaa.com
License: MIT
Platform: UNKNOWN
Classifier: License :: OSI Approved :: MIT License
Classifier: Programming Language :: Python :: 3.6
Classifier: Programming Language :: Python :: 3.7
Classifier: Programming Language :: Python :: 3.8
